tdt/__init__.py
tdt/abstract_ring_buffer.py
tdt/constants.py
tdt/convert.py
tdt/dsp_buffer.py
tdt/dsp_circuit.py
tdt/dsp_error.py
tdt/dsp_process.py
tdt/dsp_project.py
tdt/dsp_server.py
tdt/shared_ring_buffer.py
tdt/test_io_speed.py
tdt/test_process.py
tdt/tests.py
tdt/util.py
tdt/version.py
tdt/actxobjects/PA5x.py
tdt/actxobjects/RPcoX.py
tdt/actxobjects/TDevAccX.py
tdt/actxobjects/TTank.py
tdt/actxobjects/TTankEng.py
tdt/actxobjects/TTankInterfaces.py
tdt/actxobjects/TTankX.py
tdt/actxobjects/ZBUSx.py
tdt/actxobjects/__init__.py
tdt/components/AnalogInput.rcm
tdt/components/AnalogOutput.rcm
tdt/components/__init__.py
tdt/components/data_reduction.rcx
tdt/components/test_RZ6_audio_out.rcx
tdt/components/test_physiology_RZ5.rcx
tdt/components/test_physiology_RZ6.rcx
tdt/components/test_read.rcx
tdt/debuggers/RZ6_audio_out_template.rcx
tdt/debuggers/debug_RZ6_audio_out.py
tdt/device/RZ6.py
tdt/device/__init__.py
TDTPy-0.10.4.dist-info/LICENSE.txt
TDTPy-0.10.4.dist-info/METADATA
TDTPy-0.10.4.dist-info/WHEEL
TDTPy-0.10.4.dist-info/top_level.txt
TDTPy-0.10.4.dist-info/RECORD
