Metadata-Version: 2.1
Name: TDTPy
Version: 0.10.4
Summary: Module for communicating with TDT's System 3 hardware
Author-email: Brad Buran <bburan@alum.mit.edu>, Brad Buran <info@bradburan.com>, Eric Larson <larson.eric.d@gmail.com>
Maintainer-email: Brad Buran <bburan@alum.mit.edu>, Eric Larson <larson.eric.d@gmail.com>
License: Copyright © 2011-2015, authors of TDTpy
Project-URL: homepage, http://tdtpy.readthedocs.org
Project-URL: repository, https://github.com/labsn/tdtpy
Classifier: Development Status :: 4 - Beta
Classifier: Intended Audience :: Science/Research
Classifier: Programming Language :: Python
Classifier: Topic :: Scientific/Engineering
Classifier: Topic :: System :: Hardware
Classifier: License :: OSI Approved
Requires-Python: >=3.7
License-File: LICENSE.txt
Requires-Dist: pywin32
Requires-Dist: numpy
Requires-Dist: packaging
Requires-Dist: setuptools >=65
Requires-Dist: importlib-metadata ; python_version < "3.8"
Provides-Extra: docs
Requires-Dist: sphinx ; extra == 'docs'
Provides-Extra: test
Requires-Dist: pytest ; extra == 'test'
